{
  "events": [
    {
      "title": "Football Game",
      "start_date": "2022-09-15",
      "start_time": "15:42",
      "end_date": "2022-09-15",
      "end_time": "17:42",
      "description": "Lorem ipsum dolor sit amet, consectetur adipiscing elit. In nec est vitae arcu eleifend dignissim. Mauris in purus eget augue tincidunt dignissim non at libero. Cras non dui consectetur, tincidunt.",
      "image": {},
      "type": "Sport",
      "place": "Lorem ipsum",
      "phone_number": "324443349",
      "email": "abc@abc.pl",
      "id": 1
    },
    {
      "title": "Lorem ipsum",
      "start_date": "2022-09-17",
      "start_time": "18:00",
      "end_date": "2022-09-20",
      "end_time": "18:00",
      "description": "Lorem ipsum dolor sit amet, consectetur adipiscing elit. In nec est vitae arcu eleifend dignissim. Mauris in purus eget augue tincidunt dignissim non at libero. Cras non dui consectetur, tincidunt.",
      "image": {},
      "type": "Culture",
      "place": "Lorem ipsum",
      "phone_number": "324443349",
      "email": "abc@abc.pl",
      "id": 2
    },
    {
      "title": "Lorem ipsum dolor",
      "start_date": "2022-10-25",
      "start_time": "15:42",
      "end_date": "2022-11-15",
      "end_time": "17:42",
      "description": "Lorem ipsum dolor sit amet, consectetur adipiscing elit. In nec est vitae arcu eleifend dignissim. Mauris in purus eget augue tincidunt dignissim non at libero. Cras non dui consectetur, tincidunt.",
      "image": {},
      "type": "Health",
      "place": "Lorem ipsum",
      "phone_number": "324443349",
      "email": "abc@abc.pl",
      "id": 3
    },
    {
      "title": "Footbal Game",
      "start_date": "2022-09-15",
      "start_time": "15:42",
      "end_date": "2022-09-15",
      "end_time": "17:42",
      "description": "Lorem ipsum dolor sit amet, consectetur adipiscing elit. In nec est vitae arcu eleifend dignissim. Mauris in purus eget augue tincidunt dignissim non at libero. Cras non dui consectetur, tincidunt.",
      "image": {},
      "type": "Culture",
      "place": "Lorem ipsum",
      "phone_number": "324443349",
      "email": "abc@abc.pl",
      "id": 4
    }
  ]
}